{
    "1_structural_static": {
        "decomposition": {
            "partition1": [
                {
                    "id": "MongoDealersRepository"
                },
                {
                    "id": "MongoOrderRepository"
                },
                {
                    "id": "MongoShipmentRepository"
                },
                {
                    "id": "Order"
                },
                {
                    "id": "OrderController"
                },
                {
                    "id": "OrderUpdateInfo"
                },
                {
                    "id": "QuoteRepository"
                },
                {
                    "id": "Utility"
                }
            ],
            "partition10": [
                {
                    "id": "[duplicate (partition10)] Quote"
                },
                {
                    "id": "ShipmentRecord"
                },
                {
                    "id": "TestPath"
                }
            ],
            "partition11": [
                {
                    "id": "MongoCatalogItemsRepository"
                },
                {
                    "id": "OrderEventInfo"
                },
                {
                    "id": "OrderingInitializer"
                }
            ],
            "partition12": [
                {
                    "id": "PhoneInfo"
                }
            ],
            "partition2": [
                {
                    "id": "SimpleCORSFilter"
                }
            ],
            "partition3": [
                {
                    "id": "Delivery"
                },
                {
                    "id": "OrderStatus"
                }
            ],
            "partition4": [
                {
                    "id": "[duplicate (partition4)] CatalogItem"
                },
                {
                    "id": "DealersRepository"
                },
                {
                    "id": "MockDealersRepository"
                },
                {
                    "id": "QuoteDetails"
                }
            ],
            "partition5": [
                {
                    "id": "DeliveryAddress"
                },
                {
                    "id": "MongoQuoteRepository"
                },
                {
                    "id": "RepositoryFactory"
                }
            ],
            "partition6": [
                {
                    "id": "CatalogController"
                },
                {
                    "id": "DealerController"
                },
                {
                    "id": "DealerInfo"
                },
                {
                    "id": "MongoOperationsWithRetry"
                }
            ],
            "partition7": [
                {
                    "id": "QuoteController"
                },
                {
                    "id": "ShipmentController"
                }
            ],
            "partition8": [
                {
                    "id": "AppInsightsFilter"
                },
                {
                    "id": "[duplicate (partition8)] CatalogItem"
                },
                {
                    "id": "MockOrderRepository"
                },
                {
                    "id": "OrderRepository"
                },
                {
                    "id": "OrderingConfiguration"
                },
                {
                    "id": "[duplicate (partition8)] Quote"
                },
                {
                    "id": "QuoteItemInfo"
                },
                {
                    "id": "ShipmentEventInfo"
                }
            ],
            "partition9": [
                {
                    "id": "BadRequestException"
                },
                {
                    "id": "CatalogItemsRepository"
                },
                {
                    "id": "ConflictingRequestException"
                },
                {
                    "id": "MongoDBProperties"
                },
                {
                    "id": "OrderingServiceProperties"
                },
                {
                    "id": "PostgresqlProperties"
                },
                {
                    "id": "ShipmentRepository"
                }
            ]
        },
        "links": [
            {
                "source": "AppInsightsFilter",
                "target": "Utility",
                "weight": "2"
            },
            {
                "source": "ConflictingRequestException",
                "target": "BadRequestException",
                "weight": "1"
            },
            {
                "source": "OrderingConfiguration",
                "target": "OrderingServiceProperties",
                "weight": "2"
            },
            {
                "source": "OrderingConfiguration",
                "target": "Utility",
                "weight": "2"
            },
            {
                "source": "OrderingConfiguration",
                "target": "MongoDBProperties",
                "weight": "2"
            },
            {
                "source": "OrderingConfiguration",
                "target": "RepositoryFactory",
                "weight": "2"
            },
            {
                "source": "Utility",
                "target": "OrderingConfiguration",
                "weight": "1"
            },
            {
                "source": "CatalogController",
                "target": "OrderingInitializer",
                "weight": "1"
            },
            {
                "source": "CatalogController",
                "target": "Utility",
                "weight": "5"
            },
            {
                "source": "CatalogController",
                "target": "CatalogItemsRepository",
                "weight": "7"
            },
            {
                "source": "CatalogController",
                "target": "RepositoryFactory",
                "weight": "1"
            },
            {
                "source": "DealerController",
                "target": "OrderingInitializer",
                "weight": "1"
            },
            {
                "source": "DealerController",
                "target": "Utility",
                "weight": "5"
            },
            {
                "source": "DealerController",
                "target": "DealerInfo",
                "weight": "3"
            },
            {
                "source": "DealerController",
                "target": "DealersRepository",
                "weight": "7"
            },
            {
                "source": "DealerController",
                "target": "RepositoryFactory",
                "weight": "1"
            },
            {
                "source": "OrderController",
                "target": "Utility",
                "weight": "7"
            },
            {
                "source": "OrderController",
                "target": "Order",
                "weight": "4"
            },
            {
                "source": "OrderController",
                "target": "OrderEventInfo",
                "weight": "2"
            },
            {
                "source": "OrderController",
                "target": "OrderRepository",
                "weight": "10"
            },
            {
                "source": "OrderController",
                "target": "BadRequestException",
                "weight": "2"
            },
            {
                "source": "OrderController",
                "target": "ConflictingRequestException",
                "weight": "1"
            },
            {
                "source": "OrderController",
                "target": "OrderingInitializer",
                "weight": "1"
            },
            {
                "source": "OrderController",
                "target": "QuoteRepository",
                "weight": "1"
            },
            {
                "source": "OrderController",
                "target": "RepositoryFactory",
                "weight": "2"
            },
            {
                "source": "OrderController",
                "target": "OrderUpdateInfo",
                "weight": "1"
            },
            {
                "source": "QuoteController",
                "target": "BadRequestException",
                "weight": "1"
            },
            {
                "source": "QuoteController",
                "target": "OrderingInitializer",
                "weight": "1"
            },
            {
                "source": "QuoteController",
                "target": "Utility",
                "weight": "5"
            },
            {
                "source": "QuoteController",
                "target": "QuoteRepository",
                "weight": "5"
            },
            {
                "source": "QuoteController",
                "target": "RepositoryFactory",
                "weight": "1"
            },
            {
                "source": "ShipmentController",
                "target": "Utility",
                "weight": "6"
            },
            {
                "source": "ShipmentController",
                "target": "ShipmentEventInfo",
                "weight": "2"
            },
            {
                "source": "ShipmentController",
                "target": "ShipmentRepository",
                "weight": "10"
            },
            {
                "source": "ShipmentController",
                "target": "BadRequestException",
                "weight": "1"
            },
            {
                "source": "ShipmentController",
                "target": "OrderingInitializer",
                "weight": "1"
            },
            {
                "source": "ShipmentController",
                "target": "ShipmentRecord",
                "weight": "5"
            },
            {
                "source": "ShipmentController",
                "target": "Delivery",
                "weight": "4"
            },
            {
                "source": "ShipmentController",
                "target": "Order",
                "weight": "1"
            },
            {
                "source": "ShipmentController",
                "target": "OrderStatus",
                "weight": "1"
            },
            {
                "source": "ShipmentController",
                "target": "OrderRepository",
                "weight": "1"
            },
            {
                "source": "ShipmentController",
                "target": "QuoteRepository",
                "weight": "1"
            },
            {
                "source": "ShipmentController",
                "target": "RepositoryFactory",
                "weight": "3"
            },
            {
                "source": "DealerInfo",
                "target": "Utility",
                "weight": "1"
            },
            {
                "source": "Order",
                "target": "OrderStatus",
                "weight": "2"
            },
            {
                "source": "Order",
                "target": "Utility",
                "weight": "1"
            },
            {
                "source": "OrderUpdateInfo",
                "target": "OrderEventInfo",
                "weight": "1"
            },
            {
                "source": "[duplicate (partition8)] Quote",
                "target": "QuoteItemInfo",
                "weight": "1"
            },
            {
                "source": "ShipmentRecord",
                "target": "ShipmentEventInfo",
                "weight": "4"
            },
            {
                "source": "ShipmentRecord",
                "target": "DeliveryAddress",
                "weight": "1"
            },
            {
                "source": "RepositoryFactory",
                "target": "OrderingConfiguration",
                "weight": "1"
            },
            {
                "source": "RepositoryFactory",
                "target": "MockDealersRepository",
                "weight": "1"
            },
            {
                "source": "RepositoryFactory",
                "target": "MockOrderRepository",
                "weight": "1"
            },
            {
                "source": "RepositoryFactory",
                "target": "MongoCatalogItemsRepository",
                "weight": "1"
            },
            {
                "source": "RepositoryFactory",
                "target": "MongoDealersRepository",
                "weight": "1"
            },
            {
                "source": "RepositoryFactory",
                "target": "MongoOrderRepository",
                "weight": "1"
            },
            {
                "source": "RepositoryFactory",
                "target": "MongoQuoteRepository",
                "weight": "1"
            },
            {
                "source": "RepositoryFactory",
                "target": "MongoShipmentRepository",
                "weight": "1"
            },
            {
                "source": "MockDealersRepository",
                "target": "DealerInfo",
                "weight": "4"
            },
            {
                "source": "MockOrderRepository",
                "target": "BadRequestException",
                "weight": "2"
            },
            {
                "source": "MockOrderRepository",
                "target": "ConflictingRequestException",
                "weight": "1"
            },
            {
                "source": "MockOrderRepository",
                "target": "Order",
                "weight": "14"
            },
            {
                "source": "MockOrderRepository",
                "target": "OrderStatus",
                "weight": "3"
            },
            {
                "source": "MockOrderRepository",
                "target": "QuoteRepository",
                "weight": "2"
            },
            {
                "source": "MockOrderRepository",
                "target": "[duplicate (partition8)] Quote",
                "weight": "1"
            },
            {
                "source": "MockOrderRepository",
                "target": "OrderUpdateInfo",
                "weight": "2"
            },
            {
                "source": "MongoCatalogItemsRepository",
                "target": "MongoOperationsWithRetry",
                "weight": "1"
            },
            {
                "source": "MongoDealersRepository",
                "target": "MongoOperationsWithRetry",
                "weight": "1"
            },
            {
                "source": "MongoDealersRepository",
                "target": "DealerInfo",
                "weight": "1"
            },
            {
                "source": "MongoOperationsWithRetry",
                "target": "Utility",
                "weight": "1"
            },
            {
                "source": "MongoOrderRepository",
                "target": "MongoOperationsWithRetry",
                "weight": "1"
            },
            {
                "source": "MongoOrderRepository",
                "target": "BadRequestException",
                "weight": "1"
            },
            {
                "source": "MongoOrderRepository",
                "target": "ConflictingRequestException",
                "weight": "1"
            },
            {
                "source": "MongoOrderRepository",
                "target": "Order",
                "weight": "9"
            },
            {
                "source": "MongoOrderRepository",
                "target": "OrderStatus",
                "weight": "3"
            },
            {
                "source": "MongoOrderRepository",
                "target": "QuoteRepository",
                "weight": "2"
            },
            {
                "source": "MongoOrderRepository",
                "target": "OrderUpdateInfo",
                "weight": "2"
            },
            {
                "source": "MongoQuoteRepository",
                "target": "MongoOperationsWithRetry",
                "weight": "1"
            },
            {
                "source": "MongoQuoteRepository",
                "target": "BadRequestException",
                "weight": "1"
            },
            {
                "source": "MongoQuoteRepository",
                "target": "DealerInfo",
                "weight": "2"
            },
            {
                "source": "MongoQuoteRepository",
                "target": "DealersRepository",
                "weight": "4"
            },
            {
                "source": "MongoQuoteRepository",
                "target": "QuoteDetails",
                "weight": "8"
            },
            {
                "source": "MongoShipmentRepository",
                "target": "MongoOperationsWithRetry",
                "weight": "1"
            },
            {
                "source": "MongoShipmentRepository",
                "target": "ShipmentRecord",
                "weight": "4"
            },
            {
                "source": "MongoShipmentRepository",
                "target": "BadRequestException",
                "weight": "1"
            },
            {
                "source": "MongoShipmentRepository",
                "target": "ConflictingRequestException",
                "weight": "1"
            },
            {
                "source": "MongoShipmentRepository",
                "target": "OrderRepository",
                "weight": "2"
            },
            {
                "source": "MongoShipmentRepository",
                "target": "Order",
                "weight": "1"
            },
            {
                "source": "[duplicate (partition4)] CatalogItem",
                "target": "[duplicate (partition4)] CatalogItem",
                "weight": "11"
            },
            {
                "source": "[duplicate (partition8)] CatalogItem",
                "target": "[duplicate (partition8)] CatalogItem",
                "weight": "11"
            },
            {
                "source": "QuoteDetails",
                "target": "QuoteItemInfo",
                "weight": "2"
            }
        ]
    },
    "3_business_use_cases": {
        "decomposition": {
            "partition1": [
                {
                    "id": "MongoDealersRepository"
                },
                {
                    "id": "MongoOrderRepository"
                },
                {
                    "id": "MongoShipmentRepository"
                },
                {
                    "id": "Order"
                },
                {
                    "id": "OrderController"
                },
                {
                    "id": "OrderUpdateInfo"
                },
                {
                    "id": "QuoteRepository"
                },
                {
                    "id": "Utility"
                }
            ],
            "partition10": [
                {
                    "id": "[duplicate (partition10)] Quote"
                },
                {
                    "id": "ShipmentRecord"
                },
                {
                    "id": "TestPath"
                }
            ],
            "partition11": [
                {
                    "id": "MongoCatalogItemsRepository"
                },
                {
                    "id": "OrderEventInfo"
                },
                {
                    "id": "OrderingInitializer"
                }
            ],
            "partition12": [
                {
                    "id": "PhoneInfo"
                }
            ],
            "partition2": [
                {
                    "id": "SimpleCORSFilter"
                }
            ],
            "partition3": [
                {
                    "id": "Delivery"
                },
                {
                    "id": "OrderStatus"
                }
            ],
            "partition4": [
                {
                    "id": "[duplicate (partition4)] CatalogItem"
                },
                {
                    "id": "DealersRepository"
                },
                {
                    "id": "MockDealersRepository"
                },
                {
                    "id": "QuoteDetails"
                }
            ],
            "partition5": [
                {
                    "id": "DeliveryAddress"
                },
                {
                    "id": "MongoQuoteRepository"
                },
                {
                    "id": "RepositoryFactory"
                }
            ],
            "partition6": [
                {
                    "id": "CatalogController"
                },
                {
                    "id": "DealerController"
                },
                {
                    "id": "DealerInfo"
                },
                {
                    "id": "MongoOperationsWithRetry"
                }
            ],
            "partition7": [
                {
                    "id": "QuoteController"
                },
                {
                    "id": "ShipmentController"
                }
            ],
            "partition8": [
                {
                    "id": "AppInsightsFilter"
                },
                {
                    "id": "[duplicate (partition8)] CatalogItem"
                },
                {
                    "id": "MockOrderRepository"
                },
                {
                    "id": "OrderRepository"
                },
                {
                    "id": "OrderingConfiguration"
                },
                {
                    "id": "[duplicate (partition8)] Quote"
                },
                {
                    "id": "QuoteItemInfo"
                },
                {
                    "id": "ShipmentEventInfo"
                }
            ],
            "partition9": [
                {
                    "id": "BadRequestException"
                },
                {
                    "id": "CatalogItemsRepository"
                },
                {
                    "id": "ConflictingRequestException"
                },
                {
                    "id": "MongoDBProperties"
                },
                {
                    "id": "OrderingServiceProperties"
                },
                {
                    "id": "PostgresqlProperties"
                },
                {
                    "id": "ShipmentRepository"
                }
            ]
        },
        "links": []
    },
    "4_database_access": {
        "decomposition": {
            "partition1": [
                {
                    "id": "MongoDealersRepository"
                },
                {
                    "id": "MongoOrderRepository"
                },
                {
                    "id": "MongoShipmentRepository"
                },
                {
                    "id": "Order"
                },
                {
                    "id": "OrderController"
                },
                {
                    "id": "OrderUpdateInfo"
                },
                {
                    "id": "QuoteRepository"
                },
                {
                    "id": "Utility"
                }
            ],
            "partition10": [
                {
                    "id": "[duplicate (partition10)] Quote"
                },
                {
                    "id": "ShipmentRecord"
                },
                {
                    "id": "TestPath"
                }
            ],
            "partition11": [
                {
                    "id": "MongoCatalogItemsRepository"
                },
                {
                    "id": "OrderEventInfo"
                },
                {
                    "id": "OrderingInitializer"
                }
            ],
            "partition12": [
                {
                    "id": "PhoneInfo"
                }
            ],
            "partition2": [
                {
                    "id": "SimpleCORSFilter"
                }
            ],
            "partition3": [
                {
                    "id": "Delivery"
                },
                {
                    "id": "OrderStatus"
                }
            ],
            "partition4": [
                {
                    "id": "[duplicate (partition4)] CatalogItem"
                },
                {
                    "id": "DealersRepository"
                },
                {
                    "id": "MockDealersRepository"
                },
                {
                    "id": "QuoteDetails"
                }
            ],
            "partition5": [
                {
                    "id": "DeliveryAddress"
                },
                {
                    "id": "MongoQuoteRepository"
                },
                {
                    "id": "RepositoryFactory"
                }
            ],
            "partition6": [
                {
                    "id": "CatalogController"
                },
                {
                    "id": "DealerController"
                },
                {
                    "id": "DealerInfo"
                },
                {
                    "id": "MongoOperationsWithRetry"
                }
            ],
            "partition7": [
                {
                    "id": "QuoteController"
                },
                {
                    "id": "ShipmentController"
                }
            ],
            "partition8": [
                {
                    "id": "AppInsightsFilter"
                },
                {
                    "id": "[duplicate (partition8)] CatalogItem"
                },
                {
                    "id": "MockOrderRepository"
                },
                {
                    "id": "OrderRepository"
                },
                {
                    "id": "OrderingConfiguration"
                },
                {
                    "id": "[duplicate (partition8)] Quote"
                },
                {
                    "id": "QuoteItemInfo"
                },
                {
                    "id": "ShipmentEventInfo"
                }
            ],
            "partition9": [
                {
                    "id": "BadRequestException"
                },
                {
                    "id": "CatalogItemsRepository"
                },
                {
                    "id": "ConflictingRequestException"
                },
                {
                    "id": "MongoDBProperties"
                },
                {
                    "id": "OrderingServiceProperties"
                },
                {
                    "id": "PostgresqlProperties"
                },
                {
                    "id": "ShipmentRepository"
                }
            ]
        },
        "links": []
    }
}